MeCab/_MeCab.cpython-36m-i386-cygwin.dll
MeCab/_MeCab.cpython-36m-x86_64-cygwin.dll
MeCab/__init__.py
MeCab/mecabrc.in
MeCab/dic/char.bin
MeCab/dic/dicrc
MeCab/dic/matrix.bin
MeCab/dic/sys.dic
MeCab/dic/unk.dic
mecab_cygwin-0.5.0.dist-info/LICENSE.txt
mecab_cygwin-0.5.0.dist-info/METADATA
mecab_cygwin-0.5.0.dist-info/WHEEL
mecab_cygwin-0.5.0.dist-info/top_level.txt
mecab_cygwin-0.5.0.dist-info/RECORD
