Metadata-Version: 2.1
Name: mecab-cygwin
Version: 0.5.0
Summary: MeCab Python for Cygwin
Home-page: https://github.com/KoichiYasuoka/mecab-cygwin
Author: Koichi Yasuoka
Author-email: yasuoka@kanji.zinbun.kyoto-u.ac.jp
License: GPL
Project-URL: mecab-python3, https://pypi.org/projects/mecab-python3/
Project-URL: source, https://github.com/KoichiYasuoka/mecab-cygwin
Project-URL: Tracker, https://github.com/KoichiYasuoka/mecab-cygwin/issues
Keywords: mecab nlp
Platform: UNKNOWN
Classifier: License :: OSI Approved :: GNU General Public License (GPL)
Classifier: Programming Language :: Python :: 3
Classifier: Operating System :: POSIX :: Other
Classifier: Topic :: Software Development :: Libraries :: Python Modules
Classifier: Topic :: Text Processing :: Linguistic
Requires-Python: >=3.6
